LICENSE.txt
MANIFEST.in
README.rst
setup.py
multitasking/__init__.py
multitasking.egg-info/PKG-INFO
multitasking.egg-info/SOURCES.txt
multitasking.egg-info/dependency_links.txt
multitasking.egg-info/entry_points.txt
multitasking.egg-info/top_level.txt