Metadata-Version: 1.1
Name: multitasking
Version: 0.0.4
Summary: Simple async w/o async
Home-page: https://github.com/ranaroussi/multitasking
Author: Ran Aroussi
Author-email: ran@aroussi.com
License: LGPL
Keywords: multitasking async multitask threading
Platform: any
Classifier: License :: OSI Approved :: GNU Lesser General Public License v3 (LGPLv3)
Classifier: Development Status :: 4 - Beta
Classifier: Operating System :: OS Independent
Classifier: Intended Audience :: Developers
Classifier: Topic :: Software Development :: Libraries
Classifier: Topic :: Software Development :: Libraries :: Python Modules
Classifier: Programming Language :: Python :: 2.7
Classifier: Programming Language :: Python :: 3.4
Classifier: Programming Language :: Python :: 3.5
Classifier: Programming Language :: Python :: 3.6
